<?xml version="1.0" ?>
<xliff version="1.0">
  <file orginal="global" source-language="en" datatype="plaintext">
    <body>
      <trans-unit id="1">
        <source>Subscription</source>
        <target>Subskrypcja</target>
      </trans-unit>
      <trans-unit id="2">
        <source>Informations</source>
        <target>Informacje</target>
      </trans-unit>
      <trans-unit id="3">
        <source>Your Lists</source>
        <target>Listy Adresowe</target>
      </trans-unit>
      <trans-unit id="4">
        <source>Your List: %%listname%%</source>
        <target>Lista Adresowa: %%listname%%</target>
      </trans-unit>
      <trans-unit id="5">
        <source>Your Emails</source>
        <target>Adresy Pocztowe</target>
      </trans-unit>
      <trans-unit id="6">
        <source>Your Email</source>
        <target>Adres Pocztowy</target>
      </trans-unit>
      <trans-unit id="7">
        <source>Your Mailer</source>
        <target>Rozsyłacz Poczty</target>
      </trans-unit>
      <trans-unit id="8">
        <source>Email Campaigns</source>
        <target>Kampanie Pocztowe</target>
      </trans-unit>
      <trans-unit id="9">
        <source>Email Campaign</source>
        <target>Kampania Pocztowa</target>
      </trans-unit>
      <trans-unit id="10">
        <source>Autoresponder</source>
        <target>Autoresponder</target>
      </trans-unit>
      <trans-unit id="11">
        <source>Messages</source>
        <target>Wiadomości</target>
      </trans-unit>
      <trans-unit id="12">
        <source>Message</source>
        <target>Wiadomość</target>
      </trans-unit>
      <trans-unit id="13">
        <source>Message: %%subject%%</source>
        <target>Wiadomość: %%subject%%</target>
      </trans-unit>
      <trans-unit id="14">
        <source>Emails Queue</source>
        <target>Kolejka Poczty</target>
      </trans-unit>
      <trans-unit id="15">
        <source>Sent Emails</source>
        <target>Wysłana&#160;Poczta</target>
      </trans-unit>
      <trans-unit id="16">
        <source>Questions</source>
        <target>Pytania</target>
      </trans-unit>
      <trans-unit id="17">
        <source>Your Email: %%remail%%</source>
        <target>Twoje Emaile: %%remail%%</target>
      </trans-unit>
      <trans-unit id="18">
        <source>Create or edit your mailer</source>
        <target>Stwórz lub edytuj twój mailing</target>
      </trans-unit>
      <trans-unit id="19">
        <source>Templates</source>
        <target>Szablony</target>
      </trans-unit>
      <trans-unit id="20">
        <source>Template: %%tname%%</source>
        <target>Szablon: %%tname%%</target>
      </trans-unit>
    </body>
  </file>
</xliff>